CHANGES.rst
CONTRIBUTORS.rst
MANIFEST.in
README.rst
setup.cfg
setup.py
docs/LICENSE.GPL
docs/LICENSE.rst
docs/index.rst
src/collective/__init__.py
src/collective.contact.mailaction.egg-info/PKG-INFO
src/collective.contact.mailaction.egg-info/SOURCES.txt
src/collective.contact.mailaction.egg-info/dependency_links.txt
src/collective.contact.mailaction.egg-info/entry_points.txt
src/collective.contact.mailaction.egg-info/namespace_packages.txt
src/collective.contact.mailaction.egg-info/not-zip-safe
src/collective.contact.mailaction.egg-info/requires.txt
src/collective.contact.mailaction.egg-info/top_level.txt
src/collective/contact/__init__.py
src/collective/contact/mailaction/__init__.py
src/collective/contact/mailaction/adapters.py
src/collective/contact/mailaction/configure.zcml
src/collective/contact/mailaction/interfaces.py
src/collective/contact/mailaction/setuphandlers.py
src/collective/contact/mailaction/testing.py
src/collective/contact/mailaction/vocabularies.py
src/collective/contact/mailaction/browser/__init__.py
src/collective/contact/mailaction/browser/configure.zcml
src/collective/contact/mailaction/browser/actions/__init__.py
src/collective/contact/mailaction/browser/actions/default_template.pt
src/collective/contact/mailaction/browser/actions/mail.pt
src/collective/contact/mailaction/browser/actions/mail.py
src/collective/contact/mailaction/browser/actions/mail.zcml
src/collective/contact/mailaction/browser/actions/mail_utils.py
src/collective/contact/mailaction/browser/static/.gitkeep
src/collective/contact/mailaction/browser/static/send_mail.js
src/collective/contact/mailaction/locales/collective.contact.mailaction.pot
src/collective/contact/mailaction/locales/update.sh
src/collective/contact/mailaction/locales/de/LC_MESSAGES/collective.contact.mailaction.po
src/collective/contact/mailaction/locales/fr/LC_MESSAGES/collective.contact.mailaction.po
src/collective/contact/mailaction/locales/it/LC_MESSAGES/collective.contact.mailaction.po
src/collective/contact/mailaction/locales/sl/LC_MESSAGES/collective.contact.mailaction.po
src/collective/contact/mailaction/profiles/default/browserlayer.xml
src/collective/contact/mailaction/profiles/default/collectivecontactmailaction_default.txt
src/collective/contact/mailaction/profiles/default/jsregistry.xml
src/collective/contact/mailaction/profiles/default/metadata.xml
src/collective/contact/mailaction/tests/__init__.py
