Metadata-Version: 1.1
Name: collective.contact.mailaction
Version: 1.1
Summary: An add-on to send mails to contacts of collective.contacts.*
Home-page: https://pypi.python.org/pypi/collective.contact.mailaction
Author: Webmeisterei GmbH
Author-email: office@webmeisterei.com
License: GPL version 2
Keywords: Python Plone
Platform: UNKNOWN
Classifier: Environment :: Web Environment
Classifier: Framework :: Plone
Classifier: Framework :: Plone :: 4.3
Classifier: Programming Language :: Python
Classifier: Programming Language :: Python :: 2.7
Classifier: Operating System :: OS Independent
Classifier: License :: OSI Approved :: GNU General Public License v2 (GPLv2)
